datalake_utils/__init__.py
datalake_utils/utils.py
datalake_utils-2.2.1.dist-info/METADATA
datalake_utils-2.2.1.dist-info/WHEEL
datalake_utils-2.2.1.dist-info/licenses/LICENSE
datalake_utils-2.2.1.dist-info/RECORD
