Metadata-Version: 2.1
Name: datalake_utils
Version: 2.2.1
Summary: Manipulate data on Amazon S3 using Apache Hadoop filesystem compability
Project-URL: Homepage, https://github.com/yuca-live/yuca-datalake-utils
Author-email: Luis Roberto de Oliveira Moro <luis.moro@yuca.live>
License-File: LICENSE
Classifier: License :: OSI Approved :: MIT License
Classifier: Operating System :: OS Independent
Classifier: Programming Language :: Python :: 3
Classifier: Topic :: Software Development :: Libraries :: Python Modules
Requires-Python: >=3.7
Requires-Dist: boto3
Requires-Dist: fsspec
Requires-Dist: pandas
Requires-Dist: pyarrow
Requires-Dist: s3fs
